openai_autopilot/__about__.py
openai_autopilot/__init__.py
openai_autopilot/autopilot.py
openai_autopilot/exceptions.py
openai_autopilot/types.py
openai_autopilot-0.0.4.dist-info/METADATA
openai_autopilot-0.0.4.dist-info/WHEEL
openai_autopilot-0.0.4.dist-info/licenses/LICENSE.txt
openai_autopilot-0.0.4.dist-info/RECORD
