Metadata-Version: 2.1
Name: openai-autopilot
Version: 0.0.4
Summary: Autopilot enhances OpenAI interactions with concurrent task processing, faster data handling, reliable progress tracking, and transparency.
Project-URL: Documentation, https://github.com/pop-srw/openai-autopilot#readme
Project-URL: Issues, https://github.com/pop-srw/openai-autopilot/issues
Project-URL: Source, https://github.com/pop-srw/openai-autopilot
Author-email: pop-srw <khemmachotikun.s@gmail.com>
License-Expression: MIT
License-File: LICENSE.txt
Keywords: autopilot,chatgpt,gpt3.5,gpt4,openai
Classifier: Development Status :: 4 - Beta
Classifier: Programming Language :: Python
Classifier: Programming Language :: Python :: 3.8
Classifier: Programming Language :: Python :: 3.9
Classifier: Programming Language :: Python :: 3.10
Classifier: Programming Language :: Python :: 3.11
Classifier: Programming Language :: Python :: 3.12
Classifier: Programming Language :: Python :: Implementation :: CPython
Classifier: Programming Language :: Python :: Implementation :: PyPy
Requires-Python: >=3.8
Requires-Dist: asyncio
Requires-Dist: openai
Requires-Dist: pydantic
Requires-Dist: tqdm
